{"id": "8158f743-19c1-4853-8101-72cf80ebbe9d", "output": {"captions": [{"caption": "the <unk> is white", "bounding_box": [124, 386, 316, 560], "confidence": 0.9717986583709717}, {"caption": "the word <unk>", "bounding_box": [133, 289, 344, 51], "confidence": 0.9677250981330872}, {"caption": "the laptop is open", "bounding_box": [0, 0, 720, 433], "confidence": 0.9637855291366577}, {"caption": "a white laptop", "bounding_box": [0, 197, 720, 780], "confidence": 0.9590973854064941}, {"caption": "the <unk> is red", "bounding_box": [75, 75, 492, 102], "confidence": 0.9475271105766296}, {"caption": "the word <unk>", "bounding_box": [137, 475, 175, 80], "confidence": 0.9235534071922302}, {"caption": "the word <unk> on the side of the box", "bounding_box": [196, 742, 149, 71], "confidence": 0.9186398983001709}, {"caption": "a laptop on the table", "bounding_box": [493, 171, 225, 257], "confidence": 0.9153798818588257}, {"caption": "the word <unk>", "bounding_box": [131, 482, 302, 167], "confidence": 0.8850955367088318}, {"caption": "the door is open", "bounding_box": [474, 446, 245, 531], "confidence": 0.884363055229187}, {"caption": "the word <unk>", "bounding_box": [163, 629, 229, 223], "confidence": 0.8528422713279724}, {"caption": "the word <unk>", "bounding_box": [107, 195, 152, 67], "confidence": 0.8276676535606384}, {"caption": "the window is open", "bounding_box": [546, 24, 173, 593], "confidence": 0.7912008166313171}, {"caption": "the word <unk>", "bounding_box": [182, 648, 228, 69], "confidence": 0.7902006506919861}, {"caption": "a stack of books", "bounding_box": [0, 82, 37, 224], "confidence": 0.7700425386428833}, {"caption": "the window is red", "bounding_box": [0, 0, 427, 251], "confidence": 0.6847018599510193}, {"caption": "the sign is red", "bounding_box": [70, 158, 459, 411], "confidence": 0.6296067237854004}, {"caption": "the top of the laptop", "bounding_box": [487, 0, 231, 238], "confidence": 0.6292374730110168}, {"caption": "the laptop is black", "bounding_box": [0, 497, 187, 475], "confidence": 0.5282785892486572}, {"caption": "the word <unk>", "bounding_box": [163, 582, 174, 59], "confidence": 0.5068216323852539}]}}