{"id": "fec0e01b-ae84-483d-bbf6-e9114860b09e", "output": {"captions": [{"caption": "the head of a man", "bounding_box": [1714, 1069, 834, 964], "confidence": 0.956285834312439}, {"caption": "a door is open", "bounding_box": [515, 420, 425, 1599], "confidence": 0.9472129940986633}, {"caption": "the picture is yellow", "bounding_box": [0, 85, 2713, 1924], "confidence": 0.9252172708511353}, {"caption": "a white door", "bounding_box": [1494, 650, 934, 939], "confidence": 0.914205014705658}, {"caption": "the photo is black", "bounding_box": [0, 720, 2998, 3263], "confidence": 0.8308606147766113}, {"caption": "the picture is yellow", "bounding_box": [1484, 550, 1509, 1819], "confidence": 0.7740204930305481}, {"caption": "the wall is yellow", "bounding_box": [420, 0, 1184, 1434], "confidence": 0.6700232028961182}, {"caption": "the wall is yellow", "bounding_box": [2004, 0, 625, 1349], "confidence": 0.635791540145874}, {"caption": "the head of a man", "bounding_box": [1824, 1254, 390, 520], "confidence": 0.6318873763084412}, {"caption": "the word <unk>", "bounding_box": [934, 1149, 640, 225], "confidence": 0.6291835308074951}, {"caption": "a white door", "bounding_box": [1569, 794, 590, 415], "confidence": 0.6236283779144287}, {"caption": "the wall is made of wood", "bounding_box": [1819, 190, 630, 345], "confidence": 0.56486576795578}, {"caption": "the wall is dark", "bounding_box": [0, 0, 969, 2293], "confidence": 0.5236985683441162}]}}