{"id": "14227ffb-f521-4bb8-ae24-47e4aaf8ce21", "output": {"captions": [{"caption": "the picture is black and white", "bounding_box": [0, 0, 811, 872], "confidence": 0.9813774228096008}, {"caption": "the umbrella is white", "bounding_box": [0, 725, 754, 211], "confidence": 0.9639168977737427}, {"caption": "the back of a sign", "bounding_box": [277, 244, 434, 437], "confidence": 0.9568533301353455}, {"caption": "the sign is white", "bounding_box": [672, 691, 136, 235], "confidence": 0.8624654412269592}, {"caption": "a white and black sign", "bounding_box": [842, 142, 110, 344], "confidence": 0.8474723696708679}, {"caption": "the building is white", "bounding_box": [0, 875, 368, 62], "confidence": 0.8244062662124634}, {"caption": "the wall is white", "bounding_box": [676, 281, 284, 656], "confidence": 0.7968067526817322}, {"caption": "a white pole", "bounding_box": [850, 790, 50, 146], "confidence": 0.7820970416069031}, {"caption": "the wall is made of bricks", "bounding_box": [0, 176, 279, 651], "confidence": 0.7717376947402954}, {"caption": "the umbrella is black and white", "bounding_box": [307, 458, 463, 464], "confidence": 0.7611223459243774}, {"caption": "the wall is white", "bounding_box": [245, 57, 696, 395], "confidence": 0.6896059513092041}, {"caption": "a white pole", "bounding_box": [879, 146, 48, 219], "confidence": 0.6188604235649109}, {"caption": "the building is white", "bounding_box": [573, 759, 430, 177], "confidence": 0.5828993320465088}, {"caption": "the wall is made of bricks", "bounding_box": [758, 26, 247, 578], "confidence": 0.5633307695388794}, {"caption": "the fence is white", "bounding_box": [352, 905, 539, 31], "confidence": 0.5549999475479126}, {"caption": "the pole is white", "bounding_box": [711, 116, 92, 571], "confidence": 0.5371434688568115}]}}