{"id": "cceecd12-c5e4-4ba6-9ad8-efb61355362c", "output": {"captions": [{"caption": "the picture is in the background", "bounding_box": [77, 0, 721, 600], "confidence": 0.9670717716217041}, {"caption": "the top of the bag is black", "bounding_box": [294, 34, 374, 329], "confidence": 0.955483615398407}, {"caption": "the sign is black", "bounding_box": [95, 213, 574, 234], "confidence": 0.9447200894355774}, {"caption": "the word <unk>", "bounding_box": [287, 238, 404, 85], "confidence": 0.908286988735199}, {"caption": "the clouds are white", "bounding_box": [44, 16, 235, 129], "confidence": 0.8986141681671143}, {"caption": "the clouds are white", "bounding_box": [632, 0, 139, 74], "confidence": 0.8850533366203308}, {"caption": "the sky is blue", "bounding_box": [43, 0, 750, 72], "confidence": 0.8747498393058777}, {"caption": "the word <unk>", "bounding_box": [212, 340, 443, 82], "confidence": 0.8466124534606934}, {"caption": "a white book", "bounding_box": [364, 550, 104, 49], "confidence": 0.8373162746429443}, {"caption": "the background is black", "bounding_box": [212, 385, 560, 214], "confidence": 0.7753191590309143}, {"caption": "the clouds are white", "bounding_box": [206, 130, 112, 69], "confidence": 0.77334064245224}, {"caption": "the sky is blue", "bounding_box": [0, 0, 423, 272], "confidence": 0.7707902193069458}, {"caption": "the word <unk>", "bounding_box": [297, 310, 209, 51], "confidence": 0.7437346577644348}, {"caption": "the wall is white", "bounding_box": [0, 485, 265, 114], "confidence": 0.7387596368789673}, {"caption": "the top of a black bag", "bounding_box": [428, 74, 190, 183], "confidence": 0.6910379528999329}, {"caption": "the word <unk>", "bounding_box": [110, 247, 196, 50], "confidence": 0.6819038391113281}, {"caption": "the snow is white", "bounding_box": [260, 116, 279, 147], "confidence": 0.6778637170791626}, {"caption": "the sign is red", "bounding_box": [237, 288, 443, 91], "confidence": 0.6037652492523193}, {"caption": "the sky is blue", "bounding_box": [593, 0, 204, 182], "confidence": 0.5565834641456604}, {"caption": "the word <unk>", "bounding_box": [389, 377, 249, 40], "confidence": 0.5168482065200806}, {"caption": "the word <unk>", "bounding_box": [116, 213, 389, 97], "confidence": 0.5085556507110596}]}}