{"id": "97879e1c-5821-4cd7-a853-73c03d8cd739", "output": {"captions": [{"caption": "a bright yellow and yellow <unk>", "bounding_box": [612, 862, 176, 175], "confidence": 0.9804155230522156}, {"caption": "the window is red", "bounding_box": [59, 621, 1361, 457], "confidence": 0.9588513374328613}, {"caption": "a sign on the side of a truck", "bounding_box": [601, 184, 157, 169], "confidence": 0.9196029305458069}, {"caption": "the wall is red", "bounding_box": [0, 0, 598, 1080], "confidence": 0.8929686546325684}, {"caption": "a <unk> of <unk>", "bounding_box": [657, 0, 779, 1080], "confidence": 0.8778231739997864}, {"caption": "the lights are red", "bounding_box": [140, 772, 491, 270], "confidence": 0.821866512298584}, {"caption": "the sign is white", "bounding_box": [844, 290, 272, 389], "confidence": 0.809536337852478}, {"caption": "the sign is red", "bounding_box": [1202, 544, 232, 535], "confidence": 0.7976230978965759}, {"caption": "the word <unk>", "bounding_box": [770, 738, 454, 263], "confidence": 0.7807366847991943}, {"caption": "the number is red", "bounding_box": [1084, 47, 252, 128], "confidence": 0.7749614119529724}, {"caption": "the word <unk>", "bounding_box": [1202, 949, 166, 130], "confidence": 0.7747359275817871}, {"caption": "the word <unk>", "bounding_box": [1085, 0, 349, 794], "confidence": 0.7059469819068909}, {"caption": "the sign is red", "bounding_box": [83, 22, 932, 567], "confidence": 0.7033219337463379}, {"caption": "the <unk> is red", "bounding_box": [63, 470, 502, 196], "confidence": 0.6907774806022644}, {"caption": "the word <unk>", "bounding_box": [887, 367, 189, 101], "confidence": 0.678376317024231}, {"caption": "the window is red", "bounding_box": [511, 846, 625, 232], "confidence": 0.6468624472618103}, {"caption": "the word <unk>", "bounding_box": [288, 205, 140, 117], "confidence": 0.6162259578704834}, {"caption": "a red sticker", "bounding_box": [1291, 196, 86, 115], "confidence": 0.6136462688446045}, {"caption": "the window is made of wood", "bounding_box": [0, 932, 850, 146], "confidence": 0.59532231092453}, {"caption": "the window is white", "bounding_box": [887, 0, 549, 40], "confidence": 0.5848672986030579}, {"caption": "the light is red", "bounding_box": [139, 887, 81, 97], "confidence": 0.5842747688293457}, {"caption": "the number is black", "bounding_box": [1175, 371, 261, 92], "confidence": 0.569058895111084}, {"caption": "the sign is yellow", "bounding_box": [0, 524, 144, 425], "confidence": 0.5223077535629272}]}}