{"id": "03b14b2f-f5e2-41a5-a85a-2720dec5bca4", "output": {"captions": [{"caption": "a pink and white hat", "bounding_box": [892, 1312, 427, 694], "confidence": 0.9753495454788208}, {"caption": "the sign is black", "bounding_box": [547, 772, 1248, 311], "confidence": 0.9641201496124268}, {"caption": "the <unk> is <unk>", "bounding_box": [199, 2351, 1252, 322], "confidence": 0.9492784142494202}, {"caption": "the picture is open", "bounding_box": [0, 131, 2077, 2452], "confidence": 0.9421916007995605}, {"caption": "the photo is <unk>", "bounding_box": [1481, 2681, 225, 195], "confidence": 0.9110126495361328}, {"caption": "a white paper paper", "bounding_box": [1530, 1170, 221, 412], "confidence": 0.9090205430984497}, {"caption": "a door is open", "bounding_box": [15, 555, 686, 2133], "confidence": 0.9034374356269836}, {"caption": "a white toilet paper", "bounding_box": [596, 1188, 262, 277], "confidence": 0.9000983834266663}, {"caption": "the floor is red", "bounding_box": [131, 2561, 1413, 409], "confidence": 0.8520777225494385}, {"caption": "the ceiling is white", "bounding_box": [0, 0, 1980, 851], "confidence": 0.764689028263092}, {"caption": "a white toilet", "bounding_box": [585, 1095, 1162, 1293], "confidence": 0.7457377910614014}, {"caption": "the wall is open", "bounding_box": [0, 1230, 1308, 1762], "confidence": 0.7319257259368896}, {"caption": "the door is open", "bounding_box": [1923, 1083, 150, 1672], "confidence": 0.6896283030509949}, {"caption": "the photo is <unk>", "bounding_box": [165, 2422, 784, 154], "confidence": 0.6612220406532288}, {"caption": "the bird is white", "bounding_box": [795, 1631, 619, 712], "confidence": 0.5800772905349731}, {"caption": "a silver door", "bounding_box": [202, 1661, 180, 221], "confidence": 0.5662884712219238}, {"caption": "the door is open", "bounding_box": [1368, 600, 705, 2051], "confidence": 0.5369889140129089}, {"caption": "the door is open", "bounding_box": [0, 562, 300, 1830], "confidence": 0.5108910799026489}]}}