{"id": "e8748e5f-ebc1-4690-9fad-a56f0dae5b16", "output": {"captions": [{"caption": "the blanket is blue", "bounding_box": [0, 42, 668, 599], "confidence": 0.9891529083251953}, {"caption": "the cat is black", "bounding_box": [437, 339, 198, 359], "confidence": 0.982964813709259}, {"caption": "the cat is brown", "bounding_box": [399, 493, 191, 139], "confidence": 0.8529189229011536}, {"caption": "the wall is blue", "bounding_box": [225, 0, 473, 301], "confidence": 0.8285405039787292}, {"caption": "the cat is on the floor", "bounding_box": [137, 377, 453, 299], "confidence": 0.8108219504356384}, {"caption": "the blanket is blue", "bounding_box": [0, 30, 423, 283], "confidence": 0.8049163222312927}, {"caption": "the green leaves on the bed", "bounding_box": [109, 333, 217, 128], "confidence": 0.788421094417572}, {"caption": "the picture is on the ground", "bounding_box": [56, 178, 312, 308], "confidence": 0.7681801319122314}, {"caption": "the shoe is black", "bounding_box": [281, 268, 417, 296], "confidence": 0.686934769153595}, {"caption": "the ground is blue", "bounding_box": [0, 539, 425, 159], "confidence": 0.6546133160591125}, {"caption": "the green leaf on the sandwich", "bounding_box": [202, 272, 134, 147], "confidence": 0.5998572111129761}, {"caption": "a blue and yellow sign", "bounding_box": [0, 36, 30, 78], "confidence": 0.5858871936798096}, {"caption": "the blanket is white", "bounding_box": [0, 0, 276, 155], "confidence": 0.5450735688209534}, {"caption": "the blanket is blue", "bounding_box": [598, 203, 100, 467], "confidence": 0.5177443623542786}]}}