{"id": "b5686874-13c2-451e-86df-0a9f23e795bd", "output": {"captions": [{"caption": "the picture is on the wall", "bounding_box": [0, 40, 750, 1192], "confidence": 0.9806530475616455}, {"caption": "the picture is white", "bounding_box": [285, 18, 433, 745], "confidence": 0.9805301427841187}, {"caption": "the photo is black", "bounding_box": [213, 1115, 285, 100], "confidence": 0.9577882289886475}, {"caption": "the <unk> is yellow", "bounding_box": [8, 947, 638, 157], "confidence": 0.9217107892036438}, {"caption": "the <unk> is yellow", "bounding_box": [28, 802, 720, 120], "confidence": 0.9033457040786743}, {"caption": "the <unk> is pink", "bounding_box": [0, 962, 750, 367], "confidence": 0.8922317624092102}, {"caption": "the picture is white", "bounding_box": [163, 395, 585, 580], "confidence": 0.8849913477897644}, {"caption": "a brown door", "bounding_box": [0, 577, 228, 245], "confidence": 0.8693156838417053}, {"caption": "a black and white hat", "bounding_box": [537, 228, 127, 142], "confidence": 0.847835123538971}, {"caption": "the two eyes are white", "bounding_box": [262, 143, 410, 223], "confidence": 0.8433206081390381}, {"caption": "a chocolate cake", "bounding_box": [385, 373, 155, 120], "confidence": 0.8103986978530884}, {"caption": "a brown and white striped wall", "bounding_box": [0, 833, 128, 158], "confidence": 0.7401761412620544}, {"caption": "the front of a black car", "bounding_box": [288, 252, 95, 132], "confidence": 0.7193369269371033}, {"caption": "the window is white", "bounding_box": [677, 528, 72, 202], "confidence": 0.687802791595459}, {"caption": "the picture is white", "bounding_box": [427, 465, 302, 325], "confidence": 0.6801620721817017}, {"caption": "the window is open", "bounding_box": [0, 475, 142, 503], "confidence": 0.6788323521614075}, {"caption": "the word <unk>", "bounding_box": [0, 822, 392, 57], "confidence": 0.67328941822052}, {"caption": "the eye of a man", "bounding_box": [337, 177, 97, 112], "confidence": 0.6461286544799805}, {"caption": "the <unk> is white", "bounding_box": [193, 360, 200, 412], "confidence": 0.616504967212677}, {"caption": "the roof is white", "bounding_box": [0, 0, 750, 390], "confidence": 0.6090562343597412}, {"caption": "the window is open", "bounding_box": [652, 788, 97, 160], "confidence": 0.606106698513031}, {"caption": "the <unk> is white", "bounding_box": [252, 430, 387, 243], "confidence": 0.5465800166130066}]}}