{"id": "d5d2f027-f11e-40fa-9bde-f62e2d2cc088", "output": {"captions": [{"caption": "the head of a man", "bounding_box": [137, 259, 572, 855], "confidence": 0.9885789155960083}, {"caption": "the <unk> is yellow", "bounding_box": [788, 140, 945, 196], "confidence": 0.9750774502754211}, {"caption": "the picture is open", "bounding_box": [166, 194, 1206, 1305], "confidence": 0.9673219323158264}, {"caption": "the window is brown", "bounding_box": [1271, 238, 524, 963], "confidence": 0.9322991967201233}, {"caption": "a wooden fence", "bounding_box": [0, 488, 155, 657], "confidence": 0.9281486868858337}, {"caption": "the word <unk>", "bounding_box": [778, 880, 524, 243], "confidence": 0.9158263802528381}, {"caption": "the window is white", "bounding_box": [796, 184, 756, 920], "confidence": 0.8941428661346436}, {"caption": "the eyes are black", "bounding_box": [308, 621, 274, 133], "confidence": 0.8879403471946716}, {"caption": "a brown curtain", "bounding_box": [1595, 340, 171, 1159], "confidence": 0.8514681458473206}, {"caption": "the word <unk>", "bounding_box": [886, 515, 448, 119], "confidence": 0.8503484129905701}, {"caption": "the floor is white", "bounding_box": [893, 1310, 900, 189], "confidence": 0.829179048538208}, {"caption": "a brown curtain", "bounding_box": [713, 184, 180, 943], "confidence": 0.8224199414253235}, {"caption": "the shirt is black", "bounding_box": [0, 1118, 958, 380], "confidence": 0.8019245266914368}, {"caption": "the window is white", "bounding_box": [1364, 736, 284, 526], "confidence": 0.7989881634712219}, {"caption": "the word <unk>", "bounding_box": [866, 252, 367, 394], "confidence": 0.7717978954315186}, {"caption": "the word <unk>", "bounding_box": [911, 331, 292, 140], "confidence": 0.7531251907348633}, {"caption": "the wall is white", "bounding_box": [0, 0, 1796, 794], "confidence": 0.7354966998100281}, {"caption": "the eye of a black bear", "bounding_box": [434, 628, 99, 106], "confidence": 0.6856840252876282}, {"caption": "the tail is brown", "bounding_box": [1204, 821, 218, 556], "confidence": 0.6838971972465515}, {"caption": "the word <unk>", "bounding_box": [1206, 184, 587, 94], "confidence": 0.6797184944152832}, {"caption": "the wall is white", "bounding_box": [241, 0, 1433, 146], "confidence": 0.6728756427764893}, {"caption": "the word <unk>", "bounding_box": [765, 178, 536, 101], "confidence": 0.6705950498580933}, {"caption": "the curtain is brown", "bounding_box": [1246, 241, 227, 670], "confidence": 0.6560791730880737}, {"caption": "the window is open", "bounding_box": [839, 583, 954, 916], "confidence": 0.6402856707572937}, {"caption": "the word <unk>", "bounding_box": [765, 958, 338, 108], "confidence": 0.6207348108291626}, {"caption": "the tail of a brown chair", "bounding_box": [1022, 1017, 117, 295], "confidence": 0.596915602684021}, {"caption": "a yellow flower", "bounding_box": [817, 488, 130, 155], "confidence": 0.5236034393310547}]}}