{"id": "737bd2fb-f1f4-4d28-a3b3-a2fd89c1027a", "output": {"captions": [{"caption": "the grass is green", "bounding_box": [10, 197, 628, 261], "confidence": 0.9778026342391968}, {"caption": "the sky is blue", "bounding_box": [0, 0, 612, 254], "confidence": 0.9710946679115295}, {"caption": "the back of a plane", "bounding_box": [229, 201, 190, 116], "confidence": 0.9473603963851929}, {"caption": "the smoke is white", "bounding_box": [275, 55, 189, 285], "confidence": 0.935482382774353}, {"caption": "the sky is cloudy", "bounding_box": [0, 23, 240, 231], "confidence": 0.9118682742118835}, {"caption": "the sky is blue", "bounding_box": [144, 0, 494, 44], "confidence": 0.8407056331634521}, {"caption": "the trees are green", "bounding_box": [0, 239, 292, 69], "confidence": 0.7860711812973022}, {"caption": "the grass is green", "bounding_box": [380, 282, 258, 176], "confidence": 0.775505542755127}, {"caption": "the grass is green", "bounding_box": [0, 282, 250, 176], "confidence": 0.7499982118606567}, {"caption": "the trees are green", "bounding_box": [399, 243, 239, 68], "confidence": 0.7408938407897949}, {"caption": "the sky is cloudy", "bounding_box": [195, 165, 443, 132], "confidence": 0.7406877875328064}, {"caption": "the sky is white", "bounding_box": [592, 101, 45, 173], "confidence": 0.6481355428695679}, {"caption": "the window is green", "bounding_box": [134, 437, 470, 21], "confidence": 0.6468273401260376}, {"caption": "a tree in the background", "bounding_box": [9, 234, 108, 53], "confidence": 0.633241593837738}, {"caption": "the clouds are white", "bounding_box": [0, 0, 187, 116], "confidence": 0.6105369925498962}]}}