{"id": "5c62836a-3fb1-4872-aa4a-66bcc5c78ff1", "output": {"captions": [{"caption": "the sky is blue", "bounding_box": [0, 0, 1346, 841], "confidence": 0.9968444108963013}, {"caption": "the tail is black", "bounding_box": [1031, 693, 325, 314], "confidence": 0.9690812826156616}, {"caption": "the person is in the air", "bounding_box": [13, 712, 413, 261], "confidence": 0.9593562483787537}, {"caption": "a red and white wall", "bounding_box": [58, 1065, 1303, 362], "confidence": 0.9528250694274902}, {"caption": "the bird is black", "bounding_box": [49, 229, 259, 143], "confidence": 0.9480293989181519}, {"caption": "a green house", "bounding_box": [896, 944, 154, 165], "confidence": 0.9446491003036499}, {"caption": "the photo is <unk>", "bounding_box": [959, 1365, 389, 96], "confidence": 0.9338259696960449}, {"caption": "the top of the hat", "bounding_box": [494, 0, 483, 697], "confidence": 0.8936418294906616}, {"caption": "a red and white chair", "bounding_box": [73, 1080, 300, 267], "confidence": 0.8838683366775513}, {"caption": "the sky is clear", "bounding_box": [398, 285, 1040, 1157], "confidence": 0.8773554563522339}, {"caption": "the person is wearing a black shirt", "bounding_box": [182, 728, 158, 182], "confidence": 0.8306037783622742}, {"caption": "the <unk> is pink", "bounding_box": [531, 1113, 593, 205], "confidence": 0.7683067917823792}, {"caption": "a person is sitting on a chair", "bounding_box": [240, 1117, 103, 175], "confidence": 0.7530941963195801}, {"caption": "a tree in the background", "bounding_box": [0, 933, 368, 237], "confidence": 0.7403373718261719}, {"caption": "a red fence", "bounding_box": [875, 1130, 563, 191], "confidence": 0.7372737526893616}, {"caption": "the sky is clear", "bounding_box": [323, 160, 486, 894], "confidence": 0.7064310312271118}, {"caption": "the arm of a man", "bounding_box": [0, 787, 242, 141], "confidence": 0.6892386674880981}, {"caption": "the building is red", "bounding_box": [824, 1008, 614, 182], "confidence": 0.619526743888855}, {"caption": "a pole in the distance", "bounding_box": [614, 819, 69, 283], "confidence": 0.6069689989089966}, {"caption": "the trees are in the background", "bounding_box": [0, 875, 909, 424], "confidence": 0.5998391509056091}, {"caption": "the ground is red", "bounding_box": [94, 1305, 790, 176], "confidence": 0.550087571144104}, {"caption": "the top of the pole", "bounding_box": [1065, 685, 246, 115], "confidence": 0.541988730430603}, {"caption": "the sign is white", "bounding_box": [882, 1140, 100, 191], "confidence": 0.5309062004089355}, {"caption": "the sky is blue", "bounding_box": [758, 914, 631, 182], "confidence": 0.524611234664917}]}}