{"id": "f2b324c6-a2ea-45fe-99c4-8d7c0dc6f0ff", "output": {"captions": [{"caption": "the picture is open", "bounding_box": [85, 13, 742, 705], "confidence": 0.9915643930435181}, {"caption": "the picture is open", "bounding_box": [0, 393, 547, 272], "confidence": 0.9857915639877319}, {"caption": "the tv is on", "bounding_box": [12, 81, 573, 306], "confidence": 0.9780189990997314}, {"caption": "the picture is open", "bounding_box": [0, 476, 828, 390], "confidence": 0.9621239900588989}, {"caption": "the shirt is black", "bounding_box": [464, 221, 270, 509], "confidence": 0.9216225147247314}, {"caption": "the mans shirt is black", "bounding_box": [488, 590, 267, 171], "confidence": 0.8735606670379639}, {"caption": "the word <unk>", "bounding_box": [152, 467, 372, 116], "confidence": 0.8725999593734741}, {"caption": "the word <unk>", "bounding_box": [521, 508, 188, 67], "confidence": 0.8617717027664185}, {"caption": "the mans hair is black", "bounding_box": [385, 226, 284, 168], "confidence": 0.8292446136474609}, {"caption": "a picture is on the wall", "bounding_box": [324, 94, 199, 213], "confidence": 0.8262856602668762}, {"caption": "the background is green", "bounding_box": [615, 60, 212, 636], "confidence": 0.8110346794128418}, {"caption": "the top of the cake", "bounding_box": [52, 377, 436, 113], "confidence": 0.7719449996948242}, {"caption": "the bottom of the suitcase", "bounding_box": [49, 624, 416, 114], "confidence": 0.7331163287162781}, {"caption": "the screen is on", "bounding_box": [0, 142, 272, 191], "confidence": 0.7179116010665894}, {"caption": "the picture is on the table", "bounding_box": [0, 3, 351, 863], "confidence": 0.6976197361946106}, {"caption": "the window is green", "bounding_box": [115, 200, 304, 154], "confidence": 0.6779404878616333}, {"caption": "the sun is shining", "bounding_box": [468, 0, 178, 63], "confidence": 0.6573755741119385}, {"caption": "the background is green", "bounding_box": [434, 0, 393, 289], "confidence": 0.6529512405395508}, {"caption": "the wall is brown", "bounding_box": [0, 0, 737, 173], "confidence": 0.5730220675468445}, {"caption": "the background is green", "bounding_box": [17, 0, 522, 69], "confidence": 0.561020016670227}]}}