{"id": "68d58314-5430-4c01-b326-6c85cf5c8ca1", "output": {"captions": [{"caption": "the <unk> is yellow", "bounding_box": [84, 393, 305, 69], "confidence": 0.9873465895652771}, {"caption": "the sign is green", "bounding_box": [68, 340, 436, 159], "confidence": 0.9726359844207764}, {"caption": "the picture is on the wall", "bounding_box": [0, 12, 522, 456], "confidence": 0.9673069715499878}, {"caption": "a red and yellow building", "bounding_box": [333, 32, 153, 336], "confidence": 0.945375919342041}, {"caption": "the <unk> is blue", "bounding_box": [23, 0, 387, 168], "confidence": 0.9256343841552734}, {"caption": "the word <unk>", "bounding_box": [0, 14, 172, 79], "confidence": 0.8690298795700073}, {"caption": "the <unk> is blue", "bounding_box": [0, 37, 231, 226], "confidence": 0.864416778087616}, {"caption": "the word <unk>", "bounding_box": [158, 19, 206, 98], "confidence": 0.8347787261009216}, {"caption": "the word <unk>", "bounding_box": [368, 30, 194, 73], "confidence": 0.8248948454856873}, {"caption": "the sign is white", "bounding_box": [169, 0, 165, 324], "confidence": 0.7478664517402649}, {"caption": "the word <unk> on the sign", "bounding_box": [103, 422, 135, 33], "confidence": 0.6931334733963013}, {"caption": "the word <unk>", "bounding_box": [240, 393, 158, 33], "confidence": 0.6667664051055908}, {"caption": "the word <unk>", "bounding_box": [346, 108, 116, 37], "confidence": 0.6050143837928772}, {"caption": "the top of the cake is blue", "bounding_box": [127, 7, 57, 77], "confidence": 0.5800141096115112}, {"caption": "the wall is blue", "bounding_box": [441, 38, 121, 354], "confidence": 0.5706608891487122}, {"caption": "the sign is blue", "bounding_box": [49, 128, 256, 269], "confidence": 0.5694547295570374}, {"caption": "the word <unk>", "bounding_box": [205, 422, 106, 36], "confidence": 0.561965823173523}, {"caption": "the door is white", "bounding_box": [405, 475, 157, 24], "confidence": 0.5599249005317688}, {"caption": "the sign is red", "bounding_box": [315, 0, 247, 183], "confidence": 0.5270576477050781}, {"caption": "a green sign", "bounding_box": [508, 48, 38, 56], "confidence": 0.5262722969055176}, {"caption": "the background is red", "bounding_box": [158, 209, 405, 190], "confidence": 0.5054320096969604}, {"caption": "the word <unk>", "bounding_box": [81, 396, 157, 31], "confidence": 0.5043210983276367}, {"caption": "the word <unk>", "bounding_box": [30, 163, 209, 73], "confidence": 0.5000550150871277}]}}